screenrun/__init__.py
screenrun/__main__.py
screenrun/screenrun.py
screenrun-0.1.2.dist-info/LICENSE
screenrun-0.1.2.dist-info/METADATA
screenrun-0.1.2.dist-info/WHEEL
screenrun-0.1.2.dist-info/entry_points.txt
screenrun-0.1.2.dist-info/top_level.txt
screenrun-0.1.2.dist-info/RECORD
