Metadata-Version: 2.1
Name: screenrun
Version: 0.1.2
Summary: Simple process management. Keep a process running in a screen session forever.
Home-page: https://www.github.com/philiporange/screenrun
Author: Philip Orange
Classifier: License :: CC0 1.0 Universal (CC0 1.0) Public Domain Dedication
Classifier: Programming Language :: Python :: 3
Classifier: Operating System :: OS Independent
Classifier: Topic :: Utilities
License-File: LICENSE
